{
  "kind": "collectionType",
  "collectionName": "usuarios",
  "info": {
    "name": "Usuarios",
    "description": ""
  },
  "options": {
    "increments": true,
    "timestamps": true,
    "draftAndPublish": true
  },
  "pluginOptions": {},
  "attributes": {
    "nombre": {
      "type": "string",
      "required": true
    },
    "ap_paterno": {
      "type": "string",
      "required": true
    },
    "ap_materno": {
      "type": "string",
      "required": true
    },
    "fecha_nacimiento": {
      "type": "datetime",
      "required": true
    },
    "genero": {
      "type": "string",
      "required": true
    },
    "fecha_inscripcion": {
      "type": "datetime",
      "required": true
    },
    "fecha_alta": {
      "type": "datetime",
      "required": true
    },
    "rfc": {
      "type": "string",
      "maxLength": 14,
      "required": true
    },
    "curp": {
      "type": "string",
      "required": true
    },
    "nss": {
      "type": "string",
      "required": true
    },
    "tel_cel": {
      "type": "biginteger",
      "max": "10",
      "required": true
    },
    "tel_cel3": {
      "type": "string"
    },
    "email": {
      "type": "email",
      "unique": true,
      "required": true
    },
    "password": {
      "type": "string",
      "required": true
    },
    "tipo_sangre": {
      "type": "string",
      "required": true
    },
    "licencia": {
      "type": "string",
      "required": true
    },
    "alergias": {
      "type": "string",
      "required": true
    },
    "padecimientos": {
      "type": "string",
      "required": true
    },
    "nacionalidad": {
      "type": "string",
      "required": true
    },
    "calle": {
      "type": "string",
      "required": true
    },
    "numero": {
      "type": "biginteger",
      "required": true
    },
    "colonia": {
      "type": "string",
      "required": true
    },
    "cp": {
      "type": "biginteger",
      "required": true
    },
    "municipio": {
      "type": "string",
      "required": true
    },
    "ciudad": {
      "type": "string",
      "required": true
    },
    "pais": {
      "type": "string",
      "required": true
    },
    "referencia_direccion": {
      "type": "string",
      "required": true
    },
    "comment": {
      "type": "richtext",
      "required": true
    },
    "last_login": {
      "type": "datetime"
    },
    "status": {
      "type": "boolean",
      "required": true
    },
    "status2": {
      "type": "string"
    },
    "abonos": {
      "via": "usuario",
      "collection": "abonos"
    },
    "carritos": {
      "via": "usuario",
      "collection": "carrito"
    },
    "compras": {
      "via": "usuarios",
      "collection": "compras",
      "dominant": true
    },
    "creditos": {
      "via": "usuario",
      "collection": "credito"
    },
    "gastos": {
      "via": "usuario",
      "collection": "gastos"
    },
    "historiales": {
      "via": "usuario",
      "collection": "historial"
    },
    "locals": {
      "via": "usuarios",
      "collection": "local"
    },
    "metodo_pagos": {
      "via": "usuario",
      "collection": "metodo-pago"
    },
    "tipo_rol": {
      "model": "tipo-rol",
      "via": "usuarios"
    },
    "ventas": {
      "via": "usuario",
      "collection": "ventas"
    },
    "access": {
      "type": "boolean",
      "default": false
    },
    "camiones": {
      "via": "usuario",
      "collection": "camiones"
    },
    "confirm": {
      "type": "boolean",
      "default": false
    }
  }
}
